{"atualizado":"06/07/2026","kpis":{"total":2906,"concluidas":1799,"canceladas":327,"futuras":780,"virtuais":1309,"presenciais":669,"hibridas":16,"correspondente":375,"sem_nomeado_ano":1471,"desaparecidos_ano":26,"media_interna":51},"tipos":{"Perícia":423,"Julgamento":440,"Audiência":1999,"Encerramento":32,"Não especificado":11},"fases":{"Inicial":655,"Una":483,"Instrução":746,"Conciliação":51,"Conciliação Execução":59,"Ratificação Acordo":4},"natureza":{"PREVIDENCIÁRIO":42,"TRABALHISTA":2847,"CÍVEL":14,"REPRESENTAÇÃO OAB":1},"modalidade":{"Virtual":1309,"Presencial":669,"Híbrida":16},"mensal":{"2026-01":128,"2026-02":297,"2026-03":417,"2026-04":344,"2026-05":374,"2026-06":407,"2026-07":311,"2026-08":212,"2026-09":170,"2026-10":117,"2026-11":85,"2026-12":44},"producao":[{"nome":"Audiências e Pericias","total":1471,"cat":"Sem nomeado"},{"nome":"Correspondente e Prazos","total":375,"cat":"Correspondente"},{"nome":"Juliana Rodrigues de Paula","total":212,"cat":"Interno"},{"nome":"Tamyres Rodrigues Cassimiro Cirqueira","total":212,"cat":"Interno"},{"nome":"Camila Alves do Amaral Pereira","total":196,"cat":"Interno"},{"nome":"Luiz Felipe de Souza Siqueira","total":194,"cat":"Interno"},{"nome":"RICARDO GONÇALVES SILVA - EQUIPE VOI","total":76,"cat":"Interno"},{"nome":"Artur Izidoro CC","total":41,"cat":"Assistente"},{"nome":"Veronica Lenart","total":38,"cat":"Interno"},{"nome":"Oswaldo Antonio Vismar","total":33,"cat":"Interno"},{"nome":"Rafael Bacchiega","total":12,"cat":"Interno"},{"nome":"Bárbara Cristina de Oliveira","total":10,"cat":"Interno"},{"nome":"Patricia do Carmo Guides Andrade","total":9,"cat":"Interno"},{"nome":"Gabriela Natacha de Oliveira Martinez","total":8,"cat":"Interno"},{"nome":"Vinicius Giampaulo André","total":7,"cat":"Interno"},{"nome":"Vania Cristina Magrini","total":4,"cat":"Interno"},{"nome":"Rafael Izidoro Bello Gonçalves Silva","total":2,"cat":"Interno"},{"nome":"Jose Alexandre Crescenzio - VOI Advogados","total":1,"cat":"Interno"},{"nome":"Rafael Oliveira dos Santos","total":1,"cat":"Interno"},{"nome":"Laura Guimarães Felgar","total":1,"cat":"Interno"},{"nome":"Jaqueline Seleber Pizarro","total":1,"cat":"Interno"},{"nome":"Daniela Fiorini Santos","total":1,"cat":"Interno"},{"nome":"Claudia Bearzotti Pompeu","total":1,"cat":"Interno"}],"heatmap":{"fases":["Inicial","Instrução","Una","Conciliação","Conciliação Execução"],"advs":[{"nome":"Tamyres Rodrigues Cassimiro Cirqueira","vals":[74,77,55,3,0],"total":209},{"nome":"Juliana Rodrigues de Paula","vals":[66,95,44,1,2],"total":208},{"nome":"Camila Alves do Amaral Pereira","vals":[94,53,43,5,0],"total":195},{"nome":"Luiz Felipe de Souza Siqueira","vals":[59,74,32,3,0],"total":168},{"nome":"RICARDO GONÇALVES SILVA - EQUIPE VOI","vals":[20,1,2,14,31],"total":68},{"nome":"Veronica Lenart","vals":[27,4,5,1,0],"total":37},{"nome":"Oswaldo Antonio Vismar","vals":[0,0,0,17,16],"total":33},{"nome":"Rafael Bacchiega","vals":[2,2,2,1,1],"total":8},{"nome":"Gabriela Natacha de Oliveira Martinez","vals":[7,0,0,0,0],"total":7},{"nome":"Patricia do Carmo Guides Andrade","vals":[7,0,0,0,0],"total":7},{"nome":"Vania Cristina Magrini","vals":[1,2,0,0,0],"total":3},{"nome":"Rafael Izidoro Bello Gonçalves Silva","vals":[0,1,0,0,1],"total":2},{"nome":"Vinicius Giampaulo André","vals":[1,0,0,0,0],"total":1},{"nome":"Laura Guimarães Felgar","vals":[1,0,0,0,0],"total":1},{"nome":"Jaqueline Seleber Pizarro","vals":[1,0,0,0,0],"total":1},{"nome":"Daniela Fiorini Santos","vals":[1,0,0,0,0],"total":1},{"nome":"Claudia Bearzotti Pompeu","vals":[1,0,0,0,0],"total":1},{"nome":"Jose Alexandre Crescenzio - VOI Advogados","vals":[0,0,0,0,0],"total":0},{"nome":"Bárbara Cristina de Oliveira","vals":[0,0,0,0,0],"total":0},{"nome":"Rafael Oliveira dos Santos","vals":[0,0,0,0,0],"total":0}]},"mensal_adv":{"meses":["2026-01","2026-02","2026-03","2026-04","2026-05","2026-06","2026-07"],"advs":[{"nome":"Tamyres Rodrigues Cassimiro Cirqueira","vals":[15,32,41,30,36,41,17],"total":212},{"nome":"Juliana Rodrigues de Paula","vals":[16,31,45,29,32,41,17],"total":211},{"nome":"Camila Alves do Amaral Pereira","vals":[0,33,45,30,38,33,16],"total":195},{"nome":"Luiz Felipe de Souza Siqueira","vals":[17,27,42,26,32,36,14],"total":194},{"nome":"RICARDO GONÇALVES SILVA - EQUIPE VOI","vals":[9,5,21,9,8,11,13],"total":76},{"nome":"Veronica Lenart","vals":[1,5,6,8,9,8,1],"total":38},{"nome":"Oswaldo Antonio Vismar","vals":[1,10,3,11,7,1,0],"total":33},{"nome":"Rafael Bacchiega","vals":[4,3,4,1,0,0,0],"total":12},{"nome":"Bárbara Cristina de Oliveira","vals":[0,3,3,0,1,1,2],"total":10},{"nome":"Patricia do Carmo Guides Andrade","vals":[0,0,0,0,1,5,3],"total":9},{"nome":"Gabriela Natacha de Oliveira Martinez","vals":[0,1,2,0,0,0,5],"total":8},{"nome":"Vinicius Giampaulo André","vals":[0,0,0,1,1,5,0],"total":7},{"nome":"Vania Cristina Magrini","vals":[0,0,1,1,0,0,2],"total":4},{"nome":"Rafael Izidoro Bello Gonçalves Silva","vals":[0,1,0,0,0,1,0],"total":2},{"nome":"Jose Alexandre Crescenzio - VOI Advogados","vals":[0,1,0,0,0,0,0],"total":1},{"nome":"Rafael Oliveira dos Santos","vals":[0,0,1,0,0,0,0],"total":1},{"nome":"Laura Guimarães Felgar","vals":[0,0,0,0,1,0,0],"total":1},{"nome":"Jaqueline Seleber Pizarro","vals":[0,0,0,0,1,0,0],"total":1},{"nome":"Daniela Fiorini Santos","vals":[0,0,0,0,0,1,0],"total":1},{"nome":"Claudia Bearzotti Pompeu","vals":[0,0,0,0,0,1,0],"total":1}]},"alertas":{"nomeacao":[{"data":"13/07/2026","dias":7,"cliente":"Geovanni Muniz Gomes","processo":"64478017830169695","assunto":"Aud/ORD INICIAL - Virtual","responsavel":"Audiências e Pericias","notif":"Foi Notificado e Confirmou","modal":"Virtual","tipo":"Audiência"},{"data":"13/07/2026","dias":7,"cliente":"Maria Claudenice Do Nascimento","processo":"64478017830168596","assunto":"Aud/SUM - INICIAL - VIRTUAL","responsavel":"Audiências e Pericias","notif":"Foi Notificado e Confirmou","modal":"Virtual","tipo":"Audiência"},{"data":"13/07/2026","dias":7,"cliente":"Pedro Henrique de Lima","processo":"64478017830166712","assunto":"Aud/ORD - INICIAL - Presencial","responsavel":"Audiências e Pericias","notif":"Foi Notificado e Confirmou","modal":"Presencial","tipo":"Audiência"},{"data":"13/07/2026","dias":7,"cliente":"Luan Carlos Alves Batista","processo":"64478017830168435","assunto":"Aud/ORD INICIAL - Virtual","responsavel":"Audiências e Pericias","notif":"Foi Notificado e Confirmou","modal":"Virtual","tipo":"Audiência"},{"data":"13/07/2026","dias":7,"cliente":"Arlan Lima de Oliveira","processo":"64478017830168817","assunto":"Aud/SUM - INICIAL - VIRTUAL","responsavel":"Audiências e Pericias","notif":"Foi Notificado e Confirmou","modal":"Virtual","tipo":"Audiência"},{"data":"13/07/2026","dias":7,"cliente":"Andressa Cristina Da Silva","processo":"64478017830167517","assunto":"Aud/ORD - Instrução - Presencial","responsavel":"Audiências e Pericias","notif":"Foi Notificado e Confirmou","modal":"Presencial","tipo":"Audiência"},{"data":"13/07/2026","dias":7,"cliente":"Ruan Eduardo da Silva","processo":"64478017830169390","assunto":"Aud/SUM - INICIAL - VIRTUAL","responsavel":"Audiências e Pericias","notif":"Foi Notificado e Confirmou","modal":"Virtual","tipo":"Audiência"},{"data":"13/07/2026","dias":7,"cliente":"CARINA LOPES DA SILVA DE JESUS","processo":"64478017830168980","assunto":"Aud/SUM - UNA - Virtual","responsavel":"Audiências e Pericias","notif":"Foi Notificado e Confirmou","modal":"Virtual","tipo":"Audiência"},{"data":"13/07/2026","dias":7,"cliente":"Duskla de Lemos Costa Vilar","processo":"64478017830168346","assunto":"Aud/ORD - Instrução - Hibrida","responsavel":"Audiências e Pericias","notif":"Foi Notificado e Confirmou","modal":"Híbrida","tipo":"Audiência"}],"encerramento":[{"data":"13/07/2026","dias":7,"cliente":"JOSEANE SILVA SANTOS","processo":"64478017830167469","assunto":"Aud/encerramento de Instrução - Virtual","responsavel":"Audiências e Pericias","notif":"Não intimar","modal":"Virtual","tipo":"Encerramento"}],"canceladas":[{"data":"06/07/2026","dias":0,"cliente":"WÉLICA BARBOSA ARAUJO","processo":"64478017830166817","assunto":"Aud/ORD INICIAL - Virtual","responsavel":"Audiências e Pericias","notif":"Notificado do Cancelamento","modal":"Virtual","tipo":"Audiência"},{"data":"06/07/2026","dias":0,"cliente":"Karla Dayane Venceslau da Costa","processo":"64478017830168464","assunto":"Aud/ORD - UNA - Presencial","responsavel":"Audiências e Pericias","notif":"Notificado do Cancelamento","modal":"Presencial","tipo":"Audiência"},{"data":"06/07/2026","dias":0,"cliente":"WESLEY MIRANDA NASCIMENTO","processo":"64478017830169805","assunto":"Aud/ORD INICIAL - Virtual","responsavel":"Audiências e Pericias","notif":"Notificado do Cancelamento","modal":"Virtual","tipo":"Audiência"},{"data":"07/07/2026","dias":1,"cliente":"Simone Cristina de Oliveira","processo":"64478017830168576","assunto":"Aud/ORD UNA - Virtual","responsavel":"Audiências e Pericias","notif":"Notificado do Cancelamento","modal":"Virtual","tipo":"Audiência"},{"data":"07/07/2026","dias":1,"cliente":"FABIANO RIBEIRO DOS SANTOS","processo":"64478017830167366","assunto":"Aud/ORD UNA - Virtual","responsavel":"Audiências e Pericias","notif":"Notificado do Cancelamento","modal":"Virtual","tipo":"Audiência"},{"data":"08/07/2026","dias":2,"cliente":"Marcela Pereira da Silva","processo":"64478017830168456","assunto":"Aud/ORD - Instrução - Presencial","responsavel":"Correspondente e Prazos","notif":"Notificado do Cancelamento","modal":"Presencial","tipo":"Audiência"},{"data":"08/07/2026","dias":2,"cliente":"Paulo Ricardo Garcia Rocha","processo":"64478017830167636","assunto":"Aud/ORD Instrução - Virtual","responsavel":"Audiências e Pericias","notif":"Notificado do Cancelamento","modal":"Virtual","tipo":"Audiência"},{"data":"13/07/2026","dias":7,"cliente":"FELIPE CHARLES FERREIRA FLORIANO","processo":"64478017830168675","assunto":"Aud/SUM - INICIAL - VIRTUAL","responsavel":"Audiências e Pericias","notif":"Notificado do Cancelamento","modal":"Virtual","tipo":"Audiência"},{"data":"13/07/2026","dias":7,"cliente":"Paulo Roberto Ferreira Silva Bahia","processo":"3030053368","assunto":"Aud/Conciliação em Execução - VIRTUAL","responsavel":"Audiências e Pericias","notif":"Notificado do Cancelamento","modal":"Virtual","tipo":"Audiência"},{"data":"13/07/2026","dias":7,"cliente":"ELIZELLY MARTINS PIVA","processo":"64478017830169803","assunto":"(Previd) Perícia Assitente Social","responsavel":"Audiências e Pericias","notif":"Foi Notificado e Confirmou","modal":"—","tipo":"Perícia"},{"data":"13/07/2026","dias":7,"cliente":"Wesley De Souza Da Silva","processo":"64478017830166692","assunto":"Aud/ORD INICIAL - Virtual","responsavel":"Audiências e Pericias","notif":"Notificado do Cancelamento","modal":"Virtual","tipo":"Audiência"},{"data":"13/07/2026","dias":7,"cliente":"David Lucas Morais dos Reis","processo":"64478017830167876","assunto":"Aud/SUM - Instrução - VIRTUAL","responsavel":"Audiências e Pericias","notif":"Notificado do Cancelamento","modal":"Virtual","tipo":"Audiência"},{"data":"13/07/2026","dias":7,"cliente":"Sounkarou Diassy","processo":"64478017830168484","assunto":"Aud/ORD - Instrução - Presencial","responsavel":"Audiências e Pericias","notif":"Notificado do Cancelamento","modal":"Presencial","tipo":"Audiência"}],"canceladas_sem_notif":[{"data":"13/07/2026","dias":7,"cliente":"ELIZELLY MARTINS PIVA","processo":"64478017830169803","assunto":"(Previd) Perícia Assitente Social","responsavel":"Audiências e Pericias","notif":"Foi Notificado e Confirmou","modal":"—","tipo":"Perícia"}],"nao_notificado":[{"data":"08/07/2026","dias":2,"cliente":"Giovana Almagro de Oliveira","processo":"64478017830168307","assunto":"(Trab.) Perícia Ambiental","responsavel":"Correspondente e Prazos","notif":"Cliente Ainda Não Notificado","modal":"—","tipo":"Perícia"},{"data":"10/07/2026","dias":4,"cliente":"Fernando Alves queroz","processo":"64478017830169506","assunto":"(Trab.) Perícia Ambiental","responsavel":"Correspondente e Prazos","notif":"Cliente Ainda Não Notificado","modal":"—","tipo":"Perícia"}],"nao_confirmado":[{"data":"06/07/2026","dias":0,"cliente":"EMANOELLY VICTORIA SOUSA GONÇALVES","processo":"64478017830169948","assunto":"Aud/ORD - INICIAL - Presencial","responsavel":"Correspondente e Prazos","notif":"Foi Notificado","modal":"Presencial","tipo":"Audiência"},{"data":"07/07/2026","dias":1,"cliente":"Poliana Alves do Nascimento","processo":"64478017830168955","assunto":"Aud/ORD - Instrução - Presencial","responsavel":"Correspondente e Prazos","notif":"Foi Notificado","modal":"Presencial","tipo":"Audiência"},{"data":"08/07/2026","dias":2,"cliente":"Yasmin de Souza Dorneles","processo":"64478017830167510","assunto":"Aud/ORD - CONCILIAÇÃO EM CONHECIMENTO - VIRTUAL","responsavel":"Tamyres Rodrigues Cassimiro Cirqueira","notif":"Enviado E-mail","modal":"Virtual","tipo":"Audiência"},{"data":"08/07/2026","dias":2,"cliente":"Kelly Nunes Souza","processo":"64478017830167513","assunto":"(Trab.) Perícia Ambiental","responsavel":"Correspondente e Prazos","notif":"Foi Notificado","modal":"—","tipo":"Perícia"},{"data":"08/07/2026","dias":2,"cliente":"Juliana Aparecida Lemes Buono","processo":"64478017830164637","assunto":"Aud/ORD INICIAL - Virtual","responsavel":"Juliana Rodrigues de Paula","notif":"Enviado E-mail","modal":"Virtual","tipo":"Audiência"}],"desaparecidos":[],"generico_futuro":[{"data":"16/07/2026","dias":10,"cliente":"HIPOLITO FAGNER SOARES SILVA","processo":"64478017830169773","assunto":"Audiência","responsavel":"Bárbara Cristina de Oliveira","notif":"","modal":"—","tipo":"Não especificado"},{"data":"22/07/2026","dias":16,"cliente":"Nathália Fernandes de Souza","processo":"64478017830169665","assunto":"Audiência","responsavel":"Bárbara Cristina de Oliveira","notif":"Foi Notificado","modal":"—","tipo":"Não especificado"}],"generico_passado_qtd":9,"atividade":[{"data":"28/01/2026","dias":-159,"cliente":"Silvio Pessoa Belo","processo":"64478017830167911","assunto":"(Trab.) Perícia Ambiental","responsavel":"Correspondente e Prazos","notif":"Foi Notificado e Confirmou","modal":"—","tipo":"Perícia"},{"data":"28/01/2026","dias":-159,"cliente":"BARBARA DA SILVA SANTOS","processo":"64478017830167981","assunto":"Aud/ORD INICIAL - Virtual","responsavel":"Tamyres Rodrigues Cassimiro Cirqueira","notif":"Foi Notificado e Confirmou","modal":"Virtual","tipo":"Audiência"},{"data":"28/01/2026","dias":-159,"cliente":"Luana Vasconcelos Santos","processo":"64478017830168640","assunto":"Aud/ORD INICIAL - Virtual","responsavel":"Juliana Rodrigues de Paula","notif":"Foi Notificado e Confirmou","modal":"Virtual","tipo":"Audiência"},{"data":"28/01/2026","dias":-159,"cliente":"PATRICK D ANGELIS SIMOES","processo":"64478017830168710","assunto":"Aud/ORD INICIAL - Virtual","responsavel":"Luiz Felipe de Souza Siqueira","notif":"Foi Notificado e Confirmou","modal":"Virtual","tipo":"Audiência"},{"data":"27/02/2026","dias":-129,"cliente":"JOSEANE SILVA SANTOS","processo":"64478017830167469","assunto":"(Trab.) Perícia Ambiental","responsavel":"Correspondente e Prazos","notif":"Foi Notificado e Confirmou","modal":"—","tipo":"Perícia"},{"data":"04/03/2026","dias":-124,"cliente":"V.O.I - VISMAR, OLIVEIRA E IZIDORO ADVOGADOS","processo":"64478017830168333","assunto":"Audiência","responsavel":"Rafael Oliveira dos Santos","notif":"","modal":"—","tipo":"Não especificado"}],"desconhecido":[]},"notificacao":{"urgentissimo":[{"data":"08/07/2026","dias":2,"cliente":"Giovana Almagro de Oliveira","processo":"64478017830168307","assunto":"(Trab.) Perícia Ambiental","responsavel":"Correspondente e Prazos","notif":"Cliente Ainda Não Notificado","modal":"—","tipo":"Perícia"},{"data":"10/07/2026","dias":4,"cliente":"Fernando Alves queroz","processo":"64478017830169506","assunto":"(Trab.) Perícia Ambiental","responsavel":"Correspondente e Prazos","notif":"Cliente Ainda Não Notificado","modal":"—","tipo":"Perícia"}],"urgente":[{"data":"15/07/2026","dias":9,"cliente":"Jackson Douglas Ferreira","processo":"64478017830164027","assunto":"Aud/ORD - Instrução - Presencial","responsavel":"Audiências e Pericias","notif":"Cliente Ainda Não Notificado","modal":"Presencial","tipo":"Audiência"},{"data":"16/07/2026","dias":10,"cliente":"IGOR RAFAEL DE MELO","processo":"64478017830168020","assunto":"Aud/ORD INICIAL - Virtual","responsavel":"Audiências e Pericias","notif":"Cliente Ainda Não Notificado","modal":"Virtual","tipo":"Audiência"},{"data":"21/07/2026","dias":15,"cliente":"Luis Felipe Moreira dos Santos","processo":"64478017830166582","assunto":"(Trab.) Perícia Ambiental","responsavel":"Audiências e Pericias","notif":"Cliente Ainda Não Notificado","modal":"—","tipo":"Perícia"},{"data":"23/07/2026","dias":17,"cliente":"Renan Guilherme Galdino Simplicio","processo":"64478017830168679","assunto":"(Trab.) Perícia Ambiental","responsavel":"Audiências e Pericias","notif":"Cliente Ainda Não Notificado","modal":"—","tipo":"Perícia"},{"data":"28/07/2026","dias":22,"cliente":"Paulo Franco de Oliveira","processo":"64478017830169252","assunto":"(Trab.) Perícia Ambiental","responsavel":"Audiências e Pericias","notif":"Cliente Ainda Não Notificado","modal":"—","tipo":"Perícia"},{"data":"28/07/2026","dias":22,"cliente":"Ricardo Nascimento Alves","processo":"64478017830168523","assunto":"(Trab.) Perícia Ambiental","responsavel":"Audiências e Pericias","notif":"Cliente Ainda Não Notificado","modal":"—","tipo":"Perícia"},{"data":"29/07/2026","dias":23,"cliente":"MARIA JOSE DE OLIVEIRA MENDES DE SOUZA","processo":"64478017830169356","assunto":"(Trab.) Perícia Ambiental","responsavel":"Audiências e Pericias","notif":"Cliente Ainda Não Notificado","modal":"—","tipo":"Perícia"},{"data":"29/07/2026","dias":23,"cliente":"Viviane Pereira Santos","processo":"64478017830169368","assunto":"(Trab.) Perícia Ambiental","responsavel":"Audiências e Pericias","notif":"Cliente Ainda Não Notificado","modal":"—","tipo":"Perícia"},{"data":"29/07/2026","dias":23,"cliente":"Michel Amauri da Silva Rangel","processo":"64478017830169768","assunto":"(Trab.) Perícia Ambiental","responsavel":"Audiências e Pericias","notif":"Cliente Ainda Não Notificado","modal":"—","tipo":"Perícia"},{"data":"29/07/2026","dias":23,"cliente":"Robert Lincoln de Souza Braga","processo":"64478017830168564","assunto":"Aud/SUM - UNA - Virtual","responsavel":"Audiências e Pericias","notif":"Cliente Ainda Não Notificado","modal":"Virtual","tipo":"Audiência"},{"data":"29/07/2026","dias":23,"cliente":"Vagner Antonio da Silva","processo":"3030053344","assunto":"Aud/Conciliação em Execução - VIRTUAL","responsavel":"Audiências e Pericias","notif":"Cliente Ainda Não Notificado","modal":"Virtual","tipo":"Audiência"},{"data":"30/07/2026","dias":24,"cliente":"Paulo Ricardo Fiel de Lima","processo":"64478017830167984","assunto":"Aud/ORD - UNA - Presencial","responsavel":"Audiências e Pericias","notif":"Cliente Ainda Não Notificado","modal":"Presencial","tipo":"Audiência"},{"data":"31/07/2026","dias":25,"cliente":"JOSE MATHEUS GONCALVES SILVA","processo":"64478017830169704","assunto":"Aud/ORD INICIAL - Virtual","responsavel":"Audiências e Pericias","notif":"Cliente Ainda Não Notificado","modal":"Virtual","tipo":"Audiência"},{"data":"03/08/2026","dias":28,"cliente":"Ednaldo Francisco da Costa","processo":"64478017830165492","assunto":"Aud/ORD - Instrução - Hibrida","responsavel":"Audiências e Pericias","notif":"Cliente Ainda Não Notificado","modal":"Híbrida","tipo":"Audiência"},{"data":"04/08/2026","dias":29,"cliente":"Eduardo de Melo Junior","processo":"64478017830168672","assunto":"(Trab.) Perícia Ambiental","responsavel":"Audiências e Pericias","notif":"Cliente Ainda Não Notificado","modal":"—","tipo":"Perícia"},{"data":"04/08/2026","dias":29,"cliente":"Jefferson Luiz Silvestre Maia","processo":"64478017830169589","assunto":"Aud/ORD UNA - Virtual","responsavel":"Audiências e Pericias","notif":"Cliente Ainda Não Notificado","modal":"Virtual","tipo":"Audiência"},{"data":"05/08/2026","dias":30,"cliente":"Felype Rodrigues Pereira","processo":"64478017830167520","assunto":"Aud/ORD INICIAL - Virtual","responsavel":"Audiências e Pericias","notif":"Cliente Ainda Não Notificado","modal":"Virtual","tipo":"Audiência"},{"data":"05/08/2026","dias":30,"cliente":"Aluisio Carlos Fernandes","processo":"64478017830169789","assunto":"Aud/ORD INICIAL - Virtual","responsavel":"Audiências e Pericias","notif":"Cliente Ainda Não Notificado","modal":"Virtual","tipo":"Audiência"},{"data":"05/08/2026","dias":30,"cliente":"Damiana Celestino Ferreira","processo":"64478017830168568","assunto":"Aud/ORD INICIAL - Virtual","responsavel":"Audiências e Pericias","notif":"Cliente Ainda Não Notificado","modal":"Virtual","tipo":"Audiência"},{"data":"05/08/2026","dias":30,"cliente":"Evelyn Teresa Santos Costa","processo":"64478017830168671","assunto":"Aud/ORD INICIAL - Virtual","responsavel":"Audiências e Pericias","notif":"Cliente Ainda Não Notificado","modal":"Virtual","tipo":"Audiência"}],"urgente_tipo":{"Presencial":2,"Virtual":9,"Perícia":8,"Híbrida":1},"fila_total":380,"fila_mes":{"2026-08":84,"2026-09":114,"2026-10":79,"2026-11":73,"2026-12":30},"fila_tipo":{"Virtual":248,"Presencial":123,"Perícia médica":3,"Perícia":4,"Híbrida":2}},"_meta":{"linhas_descartadas_sem_data":4}}